[{"nom": "Aiglun", "cp": "06910", "dept": "06", "lat": 43.8552, "lon": 6.9348}, {"nom": "Amirat", "cp": "06910", "dept": "06", "lat": 43.8973, "lon": 6.8108}, {"nom": "Andon", "cp": "06750", "dept": "06", "lat": 43.7755, "lon": 6.8211}, {"nom": "Antibes", "cp": "06160", "dept": "06", "lat": 43.5823, "lon": 7.1048}, {"nom": "Ascros", "cp": "06260", "dept": "06", "lat": 43.9171, "lon": 7.0159}, {"nom": "Aspremont", "cp": "06790", "dept": "06", "lat": 43.7772, "lon": 7.2423}, {"nom": "Auribeau-sur-Siagne", "cp": "06810", "dept": "06", "lat": 43.6105, "lon": 6.9118}, {"nom": "Auvare", "cp": "06260", "dept": "06", "lat": 44.0062, "lon": 6.9133}, {"nom": "Bairols", "cp": "06420", "dept": "06", "lat": 43.9856, "lon": 7.1174}, {"nom": "Le Bar-sur-Loup", "cp": "06620", "dept": "06", "lat": 43.6993, "lon": 6.9674}, {"nom": "Beaulieu-sur-Mer", "cp": "06310", "dept": "06", "lat": 43.7081, "lon": 7.3324}, {"nom": "Beausoleil", "cp": "06240", "dept": "06", "lat": 43.7471, "lon": 7.4227}, {"nom": "Belvédère", "cp": "06450", "dept": "06", "lat": 44.0615, "lon": 7.3612}, {"nom": "Bendejun", "cp": "06390", "dept": "06", "lat": 43.8309, "lon": 7.2841}, {"nom": "Berre-les-Alpes", "cp": "06390", "dept": "06", "lat": 43.8342, "lon": 7.3306}, {"nom": "Beuil", "cp": "06470", "dept": "06", "lat": 44.1176, "lon": 6.9693}, {"nom": "Bézaudun-les-Alpes", "cp": "06510", "dept": "06", "lat": 43.8026, "lon": 7.0908}, {"nom": "Biot", "cp": "06410", "dept": "06", "lat": 43.6273, "lon": 7.0821}, {"nom": "Blausasc", "cp": "06440", "dept": "06", "lat": 43.7938, "lon": 7.357}, {"nom": "La Bollène-Vésubie", "cp": "06450", "dept": "06", "lat": 43.9945, "lon": 7.3749}, {"nom": "Bonson", "cp": "06830", "dept": "06", "lat": 43.8613, "lon": 7.1786}, {"nom": "Bouyon", "cp": "06510", "dept": "06", "lat": 43.8272, "lon": 7.125}, {"nom": "Breil-sur-Roya", "cp": "06540", "dept": "06", "lat": 43.9379, "lon": 7.4996}, {"nom": "Briançonnet", "cp": "06850", "dept": "06", "lat": 43.8654, "lon": 6.7325}, {"nom": "Le Broc", "cp": "06510", "dept": "06", "lat": 43.8146, "lon": 7.1621}, {"nom": "Cabris", "cp": "06530", "dept": "06", "lat": 43.6602, "lon": 6.8782}, {"nom": "Cagnes-sur-Mer", "cp": "06800", "dept": "06", "lat": 43.6712, "lon": 7.1502}, {"nom": "Caille", "cp": "06750", "dept": "06", "lat": 43.7686, "lon": 6.7544}, {"nom": "Cannes", "cp": "06150", "dept": "06", "lat": 43.5454, "lon": 7.0152}, {"nom": "Le Cannet", "cp": "06110", "dept": "06", "lat": 43.5745, "lon": 7.001}, {"nom": "Cantaron", "cp": "06340", "dept": "06", "lat": 43.7694, "lon": 7.3147}, {"nom": "Cap-d'Ail", "cp": "06320", "dept": "06", "lat": 43.7256, "lon": 7.4008}, {"nom": "Carros", "cp": "06510", "dept": "06", "lat": 43.785, "lon": 7.1798}, {"nom": "Castagniers", "cp": "06670", "dept": "06", "lat": 43.79, "lon": 7.2298}, {"nom": "Castellar", "cp": "06500", "dept": "06", "lat": 43.8227, "lon": 7.4989}, {"nom": "Castillon", "cp": "06500", "dept": "06", "lat": 43.8371, "lon": 7.4627}, {"nom": "Caussols", "cp": "06460", "dept": "06", "lat": 43.7387, "lon": 6.9071}, {"nom": "Châteauneuf-Grasse", "cp": "06740", "dept": "06", "lat": 43.6626, "lon": 6.9792}, {"nom": "Châteauneuf-Villevieille", "cp": "06390", "dept": "06", "lat": 43.8007, "lon": 7.2951}, {"nom": "Châteauneuf-d'Entraunes", "cp": "06470", "dept": "06", "lat": 44.1584, "lon": 6.8405}, {"nom": "Cipières", "cp": "06620", "dept": "06", "lat": 43.7665, "lon": 6.9229}, {"nom": "Clans", "cp": "06420", "dept": "06", "lat": 44.003, "lon": 7.1827}, {"nom": "Coaraze", "cp": "06390", "dept": "06", "lat": 43.8693, "lon": 7.3014}, {"nom": "La Colle-sur-Loup", "cp": "06480", "dept": "06", "lat": 43.6869, "lon": 7.0975}, {"nom": "Collongues", "cp": "06910", "dept": "06", "lat": 43.8934, "lon": 6.8642}, {"nom": "Colomars", "cp": "06670", "dept": "06", "lat": 43.757, "lon": 7.2212}, {"nom": "Conségudes", "cp": "06510", "dept": "06", "lat": 43.8395, "lon": 7.0395}, {"nom": "Contes", "cp": "06390", "dept": "06", "lat": 43.8133, "lon": 7.3263}, {"nom": "Courmes", "cp": "06620", "dept": "06", "lat": 43.7514, "lon": 7.0196}, {"nom": "Coursegoules", "cp": "06140", "dept": "06", "lat": 43.7898, "lon": 7.0384}, {"nom": "La Croix-sur-Roudoule", "cp": "06260", "dept": "06", "lat": 44.0032, "lon": 6.871}, {"nom": "Cuébris", "cp": "06910", "dept": "06", "lat": 43.889, "lon": 6.9955}, {"nom": "Daluis", "cp": "06470", "dept": "06", "lat": 44.0426, "lon": 6.8045}, {"nom": "Drap", "cp": "06340", "dept": "06", "lat": 43.7587, "lon": 7.3395}, {"nom": "Duranus", "cp": "06670", "dept": "06", "lat": 43.8954, "lon": 7.2796}, {"nom": "Entraunes", "cp": "06470", "dept": "06", "lat": 44.2215, "lon": 6.763}, {"nom": "L'Escarène", "cp": "06440", "dept": "06", "lat": 43.8303, "lon": 7.3665}, {"nom": "Escragnolles", "cp": "06460", "dept": "06", "lat": 43.7236, "lon": 6.7758}, {"nom": "Èze", "cp": "06360", "dept": "06", "lat": 43.7299, "lon": 7.3566}, {"nom": "Falicon", "cp": "06950", "dept": "06", "lat": 43.7533, "lon": 7.266}, {"nom": "Les Ferres", "cp": "06510", "dept": "06", "lat": 43.8424, "lon": 7.0966}, {"nom": "Fontan", "cp": "06540", "dept": "06", "lat": 44.0213, "lon": 7.5527}, {"nom": "Gars", "cp": "06850", "dept": "06", "lat": 43.8612, "lon": 6.8202}, {"nom": "Gattières", "cp": "06510", "dept": "06", "lat": 43.769, "lon": 7.1675}, {"nom": "La Gaude", "cp": "06610", "dept": "06", "lat": 43.7177, "lon": 7.1605}, {"nom": "Gilette", "cp": "06830", "dept": "06", "lat": 43.8436, "lon": 7.1602}, {"nom": "Gorbio", "cp": "06500", "dept": "06", "lat": 43.787, "lon": 7.4476}, {"nom": "Gourdon", "cp": "06620", "dept": "06", "lat": 43.7266, "lon": 6.9622}, {"nom": "Grasse", "cp": "06130", "dept": "06", "lat": 43.656, "lon": 6.937}, {"nom": "Gréolières", "cp": "06620", "dept": "06", "lat": 43.8037, "lon": 6.9296}, {"nom": "Guillaumes", "cp": "06470", "dept": "06", "lat": 44.1007, "lon": 6.8673}, {"nom": "Ilonse", "cp": "06420", "dept": "06", "lat": 44.0319, "lon": 7.0901}, {"nom": "Isola", "cp": "06420", "dept": "06", "lat": 44.1903, "lon": 7.0835}, {"nom": "Lantosque", "cp": "06450", "dept": "06", "lat": 43.9787, "lon": 7.3121}, {"nom": "Levens", "cp": "06670", "dept": "06", "lat": 43.8501, "lon": 7.2358}, {"nom": "Lieuche", "cp": "06260", "dept": "06", "lat": 44.0001, "lon": 7.0361}, {"nom": "Lucéram", "cp": "06440", "dept": "06", "lat": 43.8997, "lon": 7.3506}, {"nom": "Malaussène", "cp": "06710", "dept": "06", "lat": 43.9146, "lon": 7.1389}, {"nom": "Mandelieu-la-Napoule", "cp": "06210", "dept": "06", "lat": 43.5334, "lon": 6.918}, {"nom": "Marie", "cp": "06420", "dept": "06", "lat": 44.0319, "lon": 7.1668}, {"nom": "Le Mas", "cp": "06910", "dept": "06", "lat": 43.8388, "lon": 6.8572}, {"nom": "Massoins", "cp": "06710", "dept": "06", "lat": 43.9552, "lon": 7.1305}, {"nom": "Menton", "cp": "06500", "dept": "06", "lat": 43.7961, "lon": 7.498}, {"nom": "Mouans-Sartoux", "cp": "06370", "dept": "06", "lat": 43.6192, "lon": 6.9677}, {"nom": "Mougins", "cp": "06250", "dept": "06", "lat": 43.5931, "lon": 7.0046}, {"nom": "Moulinet", "cp": "06380", "dept": "06", "lat": 43.9503, "lon": 7.4128}, {"nom": "Les Mujouls", "cp": "06910", "dept": "06", "lat": 43.8728, "lon": 6.8649}, {"nom": "Nice", "cp": "06000", "dept": "06", "lat": 43.7032, "lon": 7.2528}, {"nom": "Opio", "cp": "06650", "dept": "06", "lat": 43.6574, "lon": 7.0094}, {"nom": "Pégomas", "cp": "06580", "dept": "06", "lat": 43.5886, "lon": 6.9213}, {"nom": "Peille", "cp": "06440", "dept": "06", "lat": 43.8043, "lon": 7.4088}, {"nom": "Peillon", "cp": "06440", "dept": "06", "lat": 43.7727, "lon": 7.3668}, {"nom": "La Penne", "cp": "06260", "dept": "06", "lat": 43.9202, "lon": 6.9361}, {"nom": "Péone", "cp": "06470", "dept": "06", "lat": 44.1333, "lon": 6.925}, {"nom": "Peymeinade", "cp": "06530", "dept": "06", "lat": 43.6289, "lon": 6.8807}, {"nom": "Pierlas", "cp": "06260", "dept": "06", "lat": 44.035, "lon": 7.0177}, {"nom": "Pierrefeu", "cp": "06910", "dept": "06", "lat": 43.8883, "lon": 7.0743}, {"nom": "Puget-Rostang", "cp": "06260", "dept": "06", "lat": 44.0056, "lon": 6.9333}, {"nom": "Puget-Théniers", "cp": "06260", "dept": "06", "lat": 43.9498, "lon": 6.9049}, {"nom": "Revest-les-Roches", "cp": "06830", "dept": "06", "lat": 43.8823, "lon": 7.1693}, {"nom": "Rigaud", "cp": "06260", "dept": "06", "lat": 43.9942, "lon": 6.976}, {"nom": "Rimplas", "cp": "06420", "dept": "06", "lat": 44.0997, "lon": 7.1449}, {"nom": "Roquebillière", "cp": "06450", "dept": "06", "lat": 44.0282, "lon": 7.2885}, {"nom": "Roquebrune-Cap-Martin", "cp": "06190", "dept": "06", "lat": 43.7638, "lon": 7.4576}, {"nom": "Roquefort-les-Pins", "cp": "06330", "dept": "06", "lat": 43.6723, "lon": 7.0565}, {"nom": "Roquestéron", "cp": "06910", "dept": "06", "lat": 43.8696, "lon": 7.0232}, {"nom": "La Roque-en-Provence", "cp": "06910", "dept": "06", "lat": 43.8494, "lon": 6.9916}, {"nom": "La Roquette-sur-Siagne", "cp": "06550", "dept": "06", "lat": 43.5853, "lon": 6.9475}, {"nom": "La Roquette-sur-Var", "cp": "06670", "dept": "06", "lat": 43.8328, "lon": 7.2072}, {"nom": "Roubion", "cp": "06420", "dept": "06", "lat": 44.1121, "lon": 7.0233}, {"nom": "Roure", "cp": "06420", "dept": "06", "lat": 44.1139, "lon": 7.0603}, {"nom": "Le Rouret", "cp": "06650", "dept": "06", "lat": 43.6803, "lon": 7.0081}, {"nom": "Sainte-Agnès", "cp": "06500", "dept": "06", "lat": 43.8046, "lon": 7.4605}, {"nom": "Saint-André-de-la-Roche", "cp": "06730", "dept": "06", "lat": 43.7455, "lon": 7.2875}, {"nom": "Saint-Antonin", "cp": "06260", "dept": "06", "lat": 43.9085, "lon": 6.9739}, {"nom": "Saint-Auban", "cp": "06850", "dept": "06", "lat": 43.8319, "lon": 6.7367}, {"nom": "Saint-Blaise", "cp": "06670", "dept": "06", "lat": 43.8132, "lon": 7.2283}, {"nom": "Saint-Cézaire-sur-Siagne", "cp": "06530", "dept": "06", "lat": 43.6592, "lon": 6.8049}, {"nom": "Saint-Dalmas-le-Selvage", "cp": "06660", "dept": "06", "lat": 44.281, "lon": 6.8452}, {"nom": "Saint-Étienne-de-Tinée", "cp": "06660", "dept": "06", "lat": 44.2597, "lon": 6.9252}, {"nom": "Saint-Jean-Cap-Ferrat", "cp": "06230", "dept": "06", "lat": 43.6883, "lon": 7.3349}, {"nom": "Saint-Jeannet", "cp": "06640", "dept": "06", "lat": 43.7619, "lon": 7.1477}, {"nom": "Saint-Laurent-du-Var", "cp": "06700", "dept": "06", "lat": 43.6865, "lon": 7.1822}, {"nom": "Saint-Léger", "cp": "06260", "dept": "06", "lat": 44.0014, "lon": 6.8189}, {"nom": "Saint-Martin-d'Entraunes", "cp": "06470", "dept": "06", "lat": 44.1453, "lon": 6.7492}, {"nom": "Saint-Martin-du-Var", "cp": "06670", "dept": "06", "lat": 43.8168, "lon": 7.2012}, {"nom": "Saint-Martin-Vésubie", "cp": "06450", "dept": "06", "lat": 44.0944, "lon": 7.307}, {"nom": "Saint-Paul-de-Vence", "cp": "06570", "dept": "06", "lat": 43.6928, "lon": 7.1196}, {"nom": "Saint-Sauveur-sur-Tinée", "cp": "06420", "dept": "06", "lat": 44.1163, "lon": 7.1226}, {"nom": "Saint-Vallier-de-Thiey", "cp": "06460", "dept": "06", "lat": 43.6994, "lon": 6.8516}, {"nom": "Sallagriffon", "cp": "06910", "dept": "06", "lat": 43.8805, "lon": 6.9117}, {"nom": "Saorge", "cp": "06540", "dept": "06", "lat": 43.9935, "lon": 7.5403}, {"nom": "Sauze", "cp": "06470", "dept": "06", "lat": 44.0862, "lon": 6.7987}, {"nom": "Séranon", "cp": "06750", "dept": "06", "lat": 43.7655, "lon": 6.6892}, {"nom": "Sigale", "cp": "06910", "dept": "06", "lat": 43.8742, "lon": 6.9652}, {"nom": "Sospel", "cp": "06380", "dept": "06", "lat": 43.8872, "lon": 7.4493}, {"nom": "Spéracèdes", "cp": "06530", "dept": "06", "lat": 43.652, "lon": 6.8573}, {"nom": "Théoule-sur-Mer", "cp": "06590", "dept": "06", "lat": 43.499, "lon": 6.9303}, {"nom": "Thiéry", "cp": "06710", "dept": "06", "lat": 43.9759, "lon": 7.0365}, {"nom": "Le Tignet", "cp": "06530", "dept": "06", "lat": 43.6257, "lon": 6.8538}, {"nom": "Toudon", "cp": "06830", "dept": "06", "lat": 43.8857, "lon": 7.1094}, {"nom": "Touët-de-l'Escarène", "cp": "06440", "dept": "06", "lat": 43.8516, "lon": 7.3799}, {"nom": "Touët-sur-Var", "cp": "06710", "dept": "06", "lat": 43.9433, "lon": 7.0091}, {"nom": "La Tour", "cp": "06420", "dept": "06", "lat": 43.9645, "lon": 7.196}, {"nom": "Tourette-du-Château", "cp": "06830", "dept": "06", "lat": 43.8812, "lon": 7.1365}, {"nom": "Tournefort", "cp": "06420", "dept": "06", "lat": 43.942, "lon": 7.1596}, {"nom": "Tourrette-Levens", "cp": "06690", "dept": "06", "lat": 43.7882, "lon": 7.275}, {"nom": "Tourrettes-sur-Loup", "cp": "06140", "dept": "06", "lat": 43.718, "lon": 7.0353}, {"nom": "La Trinité", "cp": "06340", "dept": "06", "lat": 43.7415, "lon": 7.3413}, {"nom": "La Turbie", "cp": "06320", "dept": "06", "lat": 43.7462, "lon": 7.3973}, {"nom": "Utelle", "cp": "06450", "dept": "06", "lat": 43.9392, "lon": 7.2458}, {"nom": "Valbonne", "cp": "06560", "dept": "06", "lat": 43.6267, "lon": 7.0291}, {"nom": "Valdeblore", "cp": "06420", "dept": "06", "lat": 44.1152, "lon": 7.1949}, {"nom": "Valderoure", "cp": "06750", "dept": "06", "lat": 43.7943, "lon": 6.7038}, {"nom": "Vallauris", "cp": "06220", "dept": "06", "lat": 43.5787, "lon": 7.0604}, {"nom": "Venanson", "cp": "06450", "dept": "06", "lat": 44.0412, "lon": 7.2386}, {"nom": "Vence", "cp": "06140", "dept": "06", "lat": 43.7373, "lon": 7.0995}, {"nom": "Villars-sur-Var", "cp": "06710", "dept": "06", "lat": 43.9564, "lon": 7.076}, {"nom": "Villefranche-sur-Mer", "cp": "06230", "dept": "06", "lat": 43.7081, "lon": 7.3243}, {"nom": "Villeneuve-d'Entraunes", "cp": "06470", "dept": "06", "lat": 44.1301, "lon": 6.774}, {"nom": "Villeneuve-Loubet", "cp": "06270", "dept": "06", "lat": 43.647, "lon": 7.0984}, {"nom": "La Brigue", "cp": "06430", "dept": "06", "lat": 44.0897, "lon": 7.6496}, {"nom": "Tende", "cp": "06430", "dept": "06", "lat": 44.0971, "lon": 7.5499}]